MANIFEST.in
README.rst
requirements.txt
setup.py
paasmanagerclient/__init__.py
paasmanagerclient/client.py
paasmanagerclient/environment_instance_resource_client.py
paasmanagerclient/environment_resource_client.py
paasmanagerclient/task_resource_client.py
paasmanagerclient/tier_resource_client.py
python_paasmanagerclient.egg-info/PKG-INFO
python_paasmanagerclient.egg-info/SOURCES.txt
python_paasmanagerclient.egg-info/dependency_links.txt
python_paasmanagerclient.egg-info/pbr.json
python_paasmanagerclient.egg-info/requires.txt
python_paasmanagerclient.egg-info/top_level.txt
utils/__init__.py
utils/logger_utils.py
utils/rest_client_utils.py