Metadata-Version: 1.0
Name: python-paasmanagerclient
Version: 0.0.10
Summary: PaaSManager Client
Home-page: https://github.com/telefonicaid/fiware-paas/python-paasmanagerclient
Author: jmms392
Author-email: UNKNOWN
License: UNKNOWN
Platform: UNKNOWN
